[
  {
    "slug": "2025-11-09-전역-이벤트-시스템-구현하기-1762667948508",
    "title": "전역 이벤트 시스템 구현하기",
    "date": "2025-11-09 14:59",
    "category": "SPA",
    "tags": [
      "클로저",
      "IFEE",
      "이벤트 위임",
      "이벤트 버블링"
    ],
    "thumbnail": "https://raw.githubusercontent.com/ParkYongHo1/ParkYongHo.blog/main/mdx/images/1762667948505-f2f17b58-f1aa-4845-bd23-2ef34797890f.png",
    "excerpt": "이번에는 전역 이벤트 시스템을 구현해보겠습니다.\r\n\r\n이 시스템은 “한 번의 이벤트 등록으로 여러 요소의 이벤트를 처리할 수 있게 하는 것”입니다.\r\n\r\n즉, 매번 개별 요소에 addEventListener를 붙이지 않아도, 공통된 전역 리스너가 이벤트를 감지하고 적절...",
    "readingTime": "11분"
  }
]